rda_python_dsarch/PgArch.py
rda_python_dsarch/PgMeta.py
rda_python_dsarch/__init__.py
rda_python_dsarch/ds_arch.py
rda_python_dsarch/dsarch.py
rda_python_dsarch/dsarch.usg
rda_python_dsarch/pg_arch.py
rda_python_dsarch/pg_meta.py
rda_python_dsarch-2.0.3.dist-info/licenses/LICENSE
rda_python_dsarch-2.0.3.dist-info/METADATA
rda_python_dsarch-2.0.3.dist-info/WHEEL
rda_python_dsarch-2.0.3.dist-info/entry_points.txt
rda_python_dsarch-2.0.3.dist-info/top_level.txt
rda_python_dsarch-2.0.3.dist-info/RECORD
